bolt11/__init__.py
bolt11/bit_utils.py
bolt11/cli.py
bolt11/compat.py
bolt11/decode.py
bolt11/encode.py
bolt11/exceptions.py
bolt11/models/fallback.py
bolt11/models/features.py
bolt11/models/routehint.py
bolt11/models/signature.py
bolt11/models/tags.py
bolt11/py.typed
bolt11/types.py
bolt11/utils.py
bolt11-2.1.1.dist-info/LICENSE
bolt11-2.1.1.dist-info/METADATA
bolt11-2.1.1.dist-info/WHEEL
bolt11-2.1.1.dist-info/entry_points.txt
bolt11-2.1.1.dist-info/RECORD
