Metadata-Version: 2.3
Name: bolt11
Version: 2.1.1
Summary: A library for encoding and decoding BOLT11 payment requests.
License: MIT
Author: eillarra
Author-email: eneko@illarra.com
Requires-Python: >=3.10
Classifier: License :: OSI Approved :: MIT License
Classifier: Programming Language :: Python :: 3
Classifier: Programming Language :: Python :: 3.10
Classifier: Programming Language :: Python :: 3.11
Classifier: Programming Language :: Python :: 3.12
Classifier: Programming Language :: Python :: 3.13
Requires-Dist: base58
Requires-Dist: bech32
Requires-Dist: bitstring
Requires-Dist: click
Requires-Dist: coincurve
Project-URL: Repository, https://github.com/lnbits/bolt11
